affinity_sync/__init__.py
affinity_sync/cli.py
affinity_sync/field_copier.py
affinity_sync/listener.py
affinity_sync/reader.py
affinity_sync/sync.py
affinity_sync/test.py
affinity_sync/view_builder.py
affinity_sync/writer.py
affinity_sync/clients/__init__.py
affinity_sync/clients/affinity_base.py
affinity_sync/clients/affinity_v1.py
affinity_sync/clients/affinity_v2.py
affinity_sync/clients/postgres.py
affinity_sync/module_types/__init__.py
affinity_sync/module_types/affinity_v1_api.py
affinity_sync/module_types/affinity_v2_api.py
affinity_sync/module_types/base.py
affinity_sync/module_types/db_types.py
affinity_sync/resources/schema.py
affinity_sync-72.dist-info/METADATA
affinity_sync-72.dist-info/WHEEL
affinity_sync-72.dist-info/entry_points.txt
affinity_sync-72.dist-info/top_level.txt
affinity_sync-72.dist-info/RECORD
